[{"tile":[8385,5497,14],"roads":27,"buffers":121,"notWithin":0},{"tile":[8385,5498,14],"roads":59,"buffers":365,"notWithin":0},{"tile":[8385,5496,14],"roads":1,"buffers":356,"notWithin":0},{"tile":[8386,5495,14],"roads":18,"buffers":287,"notWithin":0},{"tile":[8386,5497,14],"roads":150,"buffers":536,"notWithin":0},{"tile":[8386,5496,14],"roads":129,"buffers":636,"notWithin":0},{"tile":[8386,5498,14],"roads":191,"buffers":961,"notWithin":0},{"tile":[8386,5494,14],"roads":45,"buffers":635,"notWithin":0},{"tile":[8387,5499,14],"roads":17,"buffers":670,"notWithin":0},{"tile":[8387,5498,14],"roads":197,"buffers":1013,"notWithin":0},{"tile":[8387,5497,14],"roads":410,"buffers":1522,"notWithin":0},{"tile":[8387,5495,14],"roads":251,"buffers":1099,"notWithin":0},{"tile":[8387,5496,14],"roads":492,"buffers":1411,"notWithin":0},{"tile":[8387,5493,14],"roads":67,"buffers":788,"notWithin":0},{"tile":[8387,5492,14],"roads":3,"buffers":198,"notWithin":0},{"tile":[8388,5500,14],"roads":85,"buffers":653,"notWithin":0},{"tile":[8387,5494,14],"roads":420,"buffers":1429,"notWithin":1},{"tile":[8388,5498,14],"roads":273,"buffers":1177,"notWithin":0},{"tile":[8388,5497,14],"roads":326,"buffers":1076,"notWithin":0},{"tile":[8388,5499,14],"roads":236,"buffers":1170,"notWithin":0},{"tile":[8388,5496,14],"roads":392,"buffers":1555,"notWithin":0},{"tile":[8388,5493,14],"roads":328,"buffers":1580,"notWithin":0},{"tile":[8388,5494,14],"roads":698,"buffers":1881,"notWithin":0},{"tile":[8388,5495,14],"roads":487,"buffers":1699,"notWithin":0},{"tile":[8389,5501,14],"roads":57,"buffers":570,"notWithin":0},{"tile":[8389,5499,14],"roads":362,"buffers":1136,"notWithin":0},{"tile":[8389,5500,14],"roads":236,"buffers":825,"notWithin":1},{"tile":[8388,5492,14],"roads":282,"buffers":1773,"notWithin":0},{"tile":[8389,5498,14],"roads":356,"buffers":1136,"notWithin":0},{"tile":[8389,5497,14],"roads":584,"buffers":2514,"notWithin":0},{"tile":[8389,5494,14],"roads":533,"buffers":2125,"notWithin":0},{"tile":[8389,5496,14],"roads":718,"buffers":2851,"notWithin":0},{"tile":[8390,5500,14],"roads":135,"buffers":422,"notWithin":0},{"tile":[8389,5495,14],"roads":792,"buffers":2826,"notWithin":0},{"tile":[8390,5501,14],"roads":45,"buffers":172,"notWithin":0},{"tile":[8389,5492,14],"roads":341,"buffers":2096,"notWithin":0},{"tile":[8389,5493,14],"roads":522,"buffers":2878,"notWithin":0},{"tile":[8390,5497,14],"roads":572,"buffers":1528,"notWithin":0},{"tile":[8390,5498,14],"roads":367,"buffers":1052,"notWithin":0},{"tile":[8390,5493,14],"roads":146,"buffers":972,"notWithin":0},{"tile":[8390,5499,14],"roads":186,"buffers":749,"notWithin":0},{"tile":[8391,5500,14],"roads":114,"buffers":274,"notWithin":0},{"tile":[8390,5494,14],"roads":486,"buffers":2068,"notWithin":0},{"tile":[8391,5501,14],"roads":44,"buffers":158,"notWithin":0},{"tile":[8390,5496,14],"roads":813,"buffers":4458,"notWithin":0},{"tile":[8391,5497,14],"roads":529,"buffers":2044,"notWithin":0},{"tile":[8391,5496,14],"roads":462,"buffers":3142,"notWithin":0},{"tile":[8390,5492,14],"roads":311,"buffers":1847,"notWithin":1},{"tile":[8391,5493,14],"roads":322,"buffers":1256,"notWithin":3},{"tile":[8392,5500,14],"roads":58,"buffers":169,"notWithin":0},{"tile":[8391,5499,14],"roads":209,"buffers":708,"notWithin":0},{"tile":[8391,5492,14],"roads":266,"buffers":1983,"notWithin":0},{"tile":[8390,5495,14],"roads":856,"buffers":4735,"notWithin":0},{"tile":[8392,5496,14],"roads":552,"buffers":2401,"notWithin":0},{"tile":[8391,5502,14],"roads":2,"buffers":228,"notWithin":0},{"tile":[8392,5499,14],"roads":340,"buffers":1363,"notWithin":0},{"tile":[8392,5492,14],"roads":76,"buffers":629,"notWithin":0},{"tile":[8393,5499,14],"roads":200,"buffers":997,"notWithin":0},{"tile":[8391,5495,14],"roads":602,"buffers":2799,"notWithin":0},{"tile":[8391,5498,14],"roads":409,"buffers":1626,"notWithin":1},{"tile":[8391,5491,14],"roads":37,"buffers":801,"notWithin":0},{"tile":[8392,5495,14],"roads":691,"buffers":2310,"notWithin":0},{"tile":[8392,5491,14],"roads":58,"buffers":843,"notWithin":0},{"tile":[8391,5494,14],"roads":581,"buffers":2353,"notWithin":0},{"tile":[8392,5501,14],"roads":26,"buffers":73,"notWithin":0},{"tile":[8393,5495,14],"roads":426,"buffers":1881,"notWithin":0},{"tile":[8393,5491,14],"roads":4,"buffers":692,"notWithin":0},{"tile":[8392,5498,14],"roads":350,"buffers":1938,"notWithin":0},{"tile":[8394,5497,14],"roads":269,"buffers":822,"notWithin":0},{"tile":[8395,5499,14],"roads":36,"buffers":203,"notWithin":0},{"tile":[8395,5495,14],"roads":24,"buffers":1078,"notWithin":0},{"tile":[8393,5498,14],"roads":551,"buffers":2921,"notWithin":0},{"tile":[8392,5494,14],"roads":474,"buffers":1643,"notWithin":0},{"tile":[8393,5501,14],"roads":9,"buffers":213,"notWithin":0},{"tile":[8392,5497,14],"roads":502,"buffers":2724,"notWithin":0},{"tile":[8393,5494,14],"roads":111,"buffers":885,"notWithin":0},{"tile":[8394,5500,14],"roads":30,"buffers":104,"notWithin":0},{"tile":[8393,5497,14],"roads":290,"buffers":1165,"notWithin":0},{"tile":[8392,5493,14],"roads":254,"buffers":1227,"notWithin":0},{"tile":[8393,5500,14],"roads":86,"buffers":242,"notWithin":0},{"tile":[8393,5493,14],"roads":107,"buffers":843,"notWithin":0},{"tile":[8394,5499,14],"roads":41,"buffers":150,"notWithin":0},{"tile":[8394,5496,14],"roads":377,"buffers":1554,"notWithin":0},{"tile":[8395,5498,14],"roads":2,"buffers":163,"notWithin":0},{"tile":[8393,5496,14],"roads":516,"buffers":1990,"notWithin":0},{"tile":[8393,5492,14],"roads":130,"buffers":935,"notWithin":0},{"tile":[8394,5498,14],"roads":77,"buffers":456,"notWithin":0},{"tile":[8395,5500,14],"roads":4,"buffers":105,"notWithin":0},{"tile":[8395,5496,14],"roads":178,"buffers":764,"notWithin":0},{"tile":[8394,5495,14],"roads":254,"buffers":2725,"notWithin":0},{"tile":[8395,5497,14],"roads":110,"buffers":401,"notWithin":0}]