[{"tile":[8385,5497,14],"roads":27,"buffers":119,"notWithin":0},{"tile":[8385,5498,14],"roads":59,"buffers":346,"notWithin":0},{"tile":[8385,5496,14],"roads":1,"buffers":327,"notWithin":0},{"tile":[8386,5495,14],"roads":18,"buffers":275,"notWithin":0},{"tile":[8386,5497,14],"roads":150,"buffers":519,"notWithin":0},{"tile":[8386,5496,14],"roads":129,"buffers":603,"notWithin":0},{"tile":[8386,5498,14],"roads":191,"buffers":940,"notWithin":0},{"tile":[8386,5494,14],"roads":45,"buffers":604,"notWithin":0},{"tile":[8387,5499,14],"roads":17,"buffers":655,"notWithin":0},{"tile":[8387,5498,14],"roads":197,"buffers":1001,"notWithin":0},{"tile":[8387,5497,14],"roads":410,"buffers":1488,"notWithin":0},{"tile":[8387,5495,14],"roads":251,"buffers":1098,"notWithin":0},{"tile":[8387,5496,14],"roads":492,"buffers":1351,"notWithin":0},{"tile":[8387,5492,14],"roads":3,"buffers":197,"notWithin":0},{"tile":[8387,5493,14],"roads":67,"buffers":761,"notWithin":0},{"tile":[8388,5500,14],"roads":85,"buffers":610,"notWithin":0},{"tile":[8387,5494,14],"roads":427,"buffers":1389,"notWithin":0},{"tile":[8388,5498,14],"roads":273,"buffers":1135,"notWithin":0},{"tile":[8388,5497,14],"roads":326,"buffers":1036,"notWithin":0},{"tile":[8388,5499,14],"roads":237,"buffers":1041,"notWithin":0},{"tile":[8388,5496,14],"roads":392,"buffers":1431,"notWithin":0},{"tile":[8388,5493,14],"roads":316,"buffers":1558,"notWithin":0},{"tile":[8388,5494,14],"roads":692,"buffers":1871,"notWithin":0},{"tile":[8388,5495,14],"roads":487,"buffers":1665,"notWithin":0},{"tile":[8389,5501,14],"roads":57,"buffers":556,"notWithin":0},{"tile":[8389,5499,14],"roads":362,"buffers":1026,"notWithin":0},{"tile":[8389,5500,14],"roads":236,"buffers":782,"notWithin":0},{"tile":[8388,5492,14],"roads":284,"buffers":1752,"notWithin":0},{"tile":[8389,5498,14],"roads":356,"buffers":1042,"notWithin":0},{"tile":[8389,5497,14],"roads":584,"buffers":2276,"notWithin":0},{"tile":[8389,5494,14],"roads":527,"buffers":2008,"notWithin":0},{"tile":[8390,5500,14],"roads":135,"buffers":394,"notWithin":0},{"tile":[8389,5496,14],"roads":718,"buffers":2677,"notWithin":0},{"tile":[8389,5495,14],"roads":792,"buffers":2702,"notWithin":0},{"tile":[8390,5501,14],"roads":45,"buffers":170,"notWithin":0},{"tile":[8389,5492,14],"roads":319,"buffers":2083,"notWithin":0},{"tile":[8389,5493,14],"roads":529,"buffers":2733,"notWithin":0},{"tile":[8390,5497,14],"roads":572,"buffers":1367,"notWithin":0},{"tile":[8390,5498,14],"roads":367,"buffers":966,"notWithin":0},{"tile":[8390,5493,14],"roads":146,"buffers":818,"notWithin":0},{"tile":[8390,5499,14],"roads":186,"buffers":734,"notWithin":0},{"tile":[8391,5500,14],"roads":114,"buffers":260,"notWithin":0},{"tile":[8390,5494,14],"roads":474,"buffers":1942,"notWithin":0},{"tile":[8391,5501,14],"roads":44,"buffers":155,"notWithin":0},{"tile":[8390,5496,14],"roads":813,"buffers":4121,"notWithin":0},{"tile":[8391,5496,14],"roads":469,"buffers":2850,"notWithin":0},{"tile":[8391,5497,14],"roads":529,"buffers":1868,"notWithin":0},{"tile":[8390,5492,14],"roads":308,"buffers":1832,"notWithin":0},{"tile":[8391,5493,14],"roads":322,"buffers":1207,"notWithin":0},{"tile":[8392,5500,14],"roads":58,"buffers":164,"notWithin":0},{"tile":[8391,5499,14],"roads":209,"buffers":676,"notWithin":0},{"tile":[8391,5492,14],"roads":266,"buffers":1994,"notWithin":0},{"tile":[8392,5499,14],"roads":340,"buffers":1058,"notWithin":0},{"tile":[8390,5495,14],"roads":871,"buffers":4525,"notWithin":0},{"tile":[8391,5502,14],"roads":2,"buffers":228,"notWithin":0},{"tile":[8392,5496,14],"roads":551,"buffers":2260,"notWithin":0},{"tile":[8392,5492,14],"roads":76,"buffers":597,"notWithin":0},{"tile":[8393,5499,14],"roads":200,"buffers":630,"notWithin":0},{"tile":[8391,5495,14],"roads":603,"buffers":2644,"notWithin":0},{"tile":[8391,5498,14],"roads":409,"buffers":1561,"notWithin":1},{"tile":[8392,5495,14],"roads":687,"buffers":2196,"notWithin":0},{"tile":[8391,5491,14],"roads":37,"buffers":768,"notWithin":0},{"tile":[8392,5491,14],"roads":58,"buffers":783,"notWithin":0},{"tile":[8391,5494,14],"roads":579,"buffers":2248,"notWithin":0},{"tile":[8392,5501,14],"roads":25,"buffers":73,"notWithin":0},{"tile":[8393,5495,14],"roads":423,"buffers":1765,"notWithin":0},{"tile":[8392,5498,14],"roads":340,"buffers":1761,"notWithin":0},{"tile":[8393,5491,14],"roads":4,"buffers":652,"notWithin":0},{"tile":[8393,5498,14],"roads":550,"buffers":1957,"notWithin":0},{"tile":[8394,5497,14],"roads":253,"buffers":776,"notWithin":0},{"tile":[8395,5499,14],"roads":36,"buffers":198,"notWithin":0},{"tile":[8393,5494,14],"roads":111,"buffers":854,"notWithin":0},{"tile":[8394,5500,14],"roads":30,"buffers":104,"notWithin":0},{"tile":[8395,5495,14],"roads":24,"buffers":1038,"notWithin":0},{"tile":[8392,5494,14],"roads":471,"buffers":1589,"notWithin":0},{"tile":[8393,5501,14],"roads":9,"buffers":199,"notWithin":0},{"tile":[8392,5497,14],"roads":502,"buffers":2434,"notWithin":0},{"tile":[8393,5497,14],"roads":288,"buffers":1081,"notWithin":0},{"tile":[8394,5496,14],"roads":369,"buffers":1405,"notWithin":0},{"tile":[8395,5498,14],"roads":2,"buffers":160,"notWithin":0},{"tile":[8392,5493,14],"roads":253,"buffers":1123,"notWithin":0},{"tile":[8393,5493,14],"roads":107,"buffers":793,"notWithin":0},{"tile":[8394,5499,14],"roads":41,"buffers":97,"notWithin":0},{"tile":[8393,5500,14],"roads":86,"buffers":233,"notWithin":0},{"tile":[8393,5496,14],"roads":506,"buffers":1802,"notWithin":0},{"tile":[8393,5492,14],"roads":129,"buffers":898,"notWithin":0},{"tile":[8394,5498,14],"roads":77,"buffers":350,"notWithin":0},{"tile":[8395,5500,14],"roads":4,"buffers":100,"notWithin":0},{"tile":[8395,5496,14],"roads":178,"buffers":731,"notWithin":0},{"tile":[8394,5495,14],"roads":248,"buffers":2675,"notWithin":0},{"tile":[8395,5497,14],"roads":116,"buffers":382,"notWithin":0}]